[{"leagueId": "95a93250-2010-11e9-b945-c81f66dd2a8f", "leagueName": "Miss Fortune's Blackguards", "queueType": "RANKED_SOLO_5x5", "position": "NONE", "tier": "GOLD", "rank": "IV", "summonerId": "X7q20gxJrciTgzJsIikl-wpr9VB1y9CuIvWjxpQ6Si6YIoo", "summonerName": "ˇ1ςh Líl ξway", "leaguePoints": 0, "wins": 68, "losses": 86, "veteran": false, "inactive": false, "freshBlood": false, "hotStreak": false}, {"leagueId": "9d960b30-2d5f-11e9-87e8-c81f66dacb22", "leagueName": "Master Yi's Commanders", "queueType": "RANKED_FLEX_SR", "position": "NONE", "tier": "SILVER", "rank": "II", "summonerId": "X7q20gxJrciTgzJsIikl-wpr9VB1y9CuIvWjxpQ6Si6YIoo", "summonerName": "ˇ1ςh Líl ξway", "leaguePoints": 28, "wins": 38, "losses": 48, "veteran": false, "inactive": false, "freshBlood": false, "hotStreak": false}]