[{"leagueId": "e3385f30-27bf-11e9-9101-c81f66db01ef", "leagueName": "Nidalee's Swarm", "queueType": "RANKED_FLEX_SR", "position": "NONE", "tier": "BRONZE", "rank": "I", "summonerId": "HbDc_vtu64vKzhFPUEe8t8Tvvmcu_AOmjl92dpCjJ0Cx1y4", "summonerName": "Vn98NAM98De", "leaguePoints": 34, "wins": 7, "losses": 5, "veteran": false, "inactive": false, "freshBlood": false, "hotStreak": true}, {"leagueId": "f5458bd0-1fb8-11e9-9dcb-c81f66dd0e0d", "leagueName": "Diana's Warmongers", "queueType": "RANKED_SOLO_5x5", "position": "NONE", "tier": "GOLD", "rank": "IV", "summonerId": "HbDc_vtu64vKzhFPUEe8t8Tvvmcu_AOmjl92dpCjJ0Cx1y4", "summonerName": "Vn98NAM98De", "leaguePoints": 0, "wins": 192, "losses": 202, "veteran": true, "inactive": false, "freshBlood": false, "hotStreak": false}]