[{"leagueId": "90fc9dd0-3322-11e9-8193-c81f66db01ef", "leagueName": "Orianna's Bandits", "queueType": "RANKED_FLEX_SR", "position": "NONE", "tier": "BRONZE", "rank": "I", "summonerId": "iiNKFNHfirkKogKLjZXNQFV12P3FG-AFccLJ0iykbtn6pU0", "summonerName": "Unknown V", "leaguePoints": 91, "wins": 13, "losses": 13, "veteran": false, "inactive": false, "freshBlood": false, "hotStreak": false}, {"leagueId": "30eea760-45fd-11e9-8755-c81f66db01ef", "leagueName": "Renekton's Elite", "queueType": "RANKED_SOLO_5x5", "position": "NONE", "tier": "GOLD", "rank": "IV", "summonerId": "iiNKFNHfirkKogKLjZXNQFV12P3FG-AFccLJ0iykbtn6pU0", "summonerName": "Unknown V", "leaguePoints": 21, "wins": 176, "losses": 178, "veteran": false, "inactive": false, "freshBlood": false, "hotStreak": false}]