[{"leagueId": "59f46b10-36e2-11e9-99c8-c81f66dacb22", "leagueName": "Gragas's Host", "queueType": "RANKED_SOLO_5x5", "position": "NONE", "tier": "GOLD", "rank": "III", "summonerId": "4MlB6aMrtebxqTAUJSA1NJ1pso5rbGvaPA5sePNBiCrOr_0", "summonerName": "Popp Queen Toppy", "leaguePoints": 0, "wins": 41, "losses": 46, "veteran": false, "inactive": false, "freshBlood": false, "hotStreak": false}, {"leagueId": "a92d6710-20e7-11e9-b350-c81f66dd2a8f", "leagueName": "Olaf's Weaponmasters", "queueType": "RANKED_FLEX_SR", "position": "NONE", "tier": "SILVER", "rank": "II", "summonerId": "4MlB6aMrtebxqTAUJSA1NJ1pso5rbGvaPA5sePNBiCrOr_0", "summonerName": "Popp Queen Toppy", "leaguePoints": 18, "wins": 5, "losses": 7, "veteran": false, "inactive": false, "freshBlood": false, "hotStreak": false}]